<?xml version="1.0" encoding="UTF-8"?>
<?xml-stylesheet type="text/xsl" href="jms-forest.xsl"?>
<fr:tree
toc="true"
numbered="true"
show-heading="true"
show-metadata="true"
expanded="true"
root="false"
xmlns:fr="http://www.jonmsterling.com/jms-005P.xml"><fr:frontmatter><fr:anchor>20141</fr:anchor><fr:addr
type="user">jemlord</fr:addr><fr:route>jemlord.xml</fr:route><fr:title
text="Jem Lord">Jem Lord</fr:title><fr:taxon>Person</fr:taxon><fr:authors /><fr:meta
name="institution">University of Oxford</fr:meta><fr:meta
name="position">Student</fr:meta></fr:frontmatter><fr:mainmatter /><fr:backmatter /></fr:tree>