<?xml version="1.0" encoding="UTF-8"?>
<?xml-stylesheet type="text/xsl" href="forest.xsl"?>
<tree mode="full" root="false" taxon="Reference"><frontmatter><trail/> <anchor>23632</anchor> <addr>sterling-2021-bhfs</addr>  <route>sterling-2021-bhfs.xml</route> <date>May 19, 2021</date> <authors><author><link href="jonmsterling.xml" type="local">Jon Sterling</link></author> </authors> <title>Higher order functions and Brouwer's Thesis</title> <meta name="bibtex">
 @article{sterling:2021:bhfs,
  author = {Sterling, Jonathan},
  publisher = {Cambridge University Press},
  date = {2021},
  doi = {10.1017/S0956796821000095},
  eprint = {1608.03814},
  eprintclass = {math.LO},
  eprinttype = {arXiv},
  journaltitle = {Journal of Functional Programming},
  note = {\emph{Bob Harper Festschrift Collection}},
  pages = {e11},
  title = {Higher order functions and Brouwer's thesis},
  volume = {31},
}
 </meta><meta name="artifact">http://www.jonmsterling.com/agda-effectful-forcing/index.html</meta><meta name="doi">10.1017/S0956796821000095</meta><meta name="venue">Journal of Functional Programming, Bob Harper Festschrift Collection</meta></frontmatter> <mainmatter><p>Extending Martín Escardó's effectful forcing technique, we give a new proof of a well-known result: Brouwer's monotone bar theorem holds for any bar that can be realized by a functional of type (ℕ→ℕ)→ℕ in Gödel's System T. Effectful forcing is an elementary alternative to standard sheaf-theoretic forcing arguments, using ideas from programming languages, including computational effects, monads, the algebra interpretation of call-by-name λ-calculus, and logical relations. Our argument proceeds by interpreting System T programs as well-founded dialogue trees whose nodes branch on a query to an oracle of type ℕ→ℕ, lifted to higher type along a call-by-name translation. To connect this interpretation to the bar theorem, we then show that Brouwer's famous &quot;mental constructions&quot; of barhood constitute an invariant form of these dialogue trees in which queries to the oracle are made maximally and in order.</p></mainmatter> <backmatter><contributions/> <context/> <related/> <backlinks/> <references/></backmatter></tree>