<?xml version="1.0" encoding="UTF-8"?>
<?xml-stylesheet type="text/xsl" href="jms-forest.xsl"?>
<fr:tree
toc="true"
numbered="true"
show-heading="true"
show-metadata="true"
expanded="true"
root="false"
xmlns:fr="http://www.jonmsterling.com/jms-005P.xml"><fr:frontmatter><fr:anchor>3814</fr:anchor><fr:addr
type="machine">#305</fr:addr><fr:route>unstable-305.xml</fr:route><fr:taxon>Proof</fr:taxon><fr:date><fr:year>2024</fr:year><fr:month>2</fr:month><fr:day>17</fr:day></fr:date><fr:authors><fr:author><fr:link
type="local"
href="jonmsterling.xml"
addr="jonmsterling"
title="Jon Sterling">Jon Sterling</fr:link></fr:author></fr:authors></fr:frontmatter><fr:mainmatter>
 <fr:p>By induction on <fr:tex
display="inline"><![CDATA[n]]></fr:tex>, with the base cases following from <fr:ref
addr="erct-003V"
href="erct-003V.xml"
taxon="Corollary" /> and <fr:ref
addr="erct-001M"
href="erct-001M.xml"
taxon="Lemma" />. In the inductive step, we need to show that for all <fr:tex
display="inline"><![CDATA[u,v\colon \mathchoice {\textstyle \sum _{  \mathopen {}\left \lparen x:A\right \rparen \mathclose {} }}{\textstyle \sum _{  \mathopen {}\left \lparen x:A\right \rparen \mathclose {} }}{\scriptstyle \sum _{  \mathopen {}\left \lparen x:A\right \rparen \mathclose {} }}{\scriptscriptstyle \sum _{  \mathopen {}\left \lparen x:A\right \rparen \mathclose {} }}Bx]]></fr:tex> the identification type <fr:tex
display="inline"><![CDATA[u=v]]></fr:tex> is <fr:link
type="local"
href="erct-001G.xml"
addr="erct-001G"
title="N-truncated type"><html:span
xmlns:html="http://www.w3.org/1999/xhtml"
style="white-space: nowrap"><fr:tex
display="inline"><![CDATA[n+1]]></fr:tex>-truncated</html:span></fr:link> assuming the same of all the identification types of <fr:tex
display="inline"><![CDATA[A]]></fr:tex> and <fr:tex
display="inline"><![CDATA[Bx]]></fr:tex> for <fr:tex
display="inline"><![CDATA[x:A]]></fr:tex>. By <fr:ref
addr="erct-0035"
href="erct-0035.xml"
taxon="Definition" />, <fr:tex
display="inline"><![CDATA[u=v]]></fr:tex> is a <fr:link
type="local"
href="erct-0025.xml"
addr="erct-0025"
title="Retract">retract</fr:link> of <fr:tex
display="inline"><![CDATA[\mathchoice {\textstyle \sum _{  \mathopen {}\left \lparen p:u.1=v.1\right \rparen \mathclose {} }}{\textstyle \sum _{  \mathopen {}\left \lparen p:u.1=v.1\right \rparen \mathclose {} }}{\scriptstyle \sum _{  \mathopen {}\left \lparen p:u.1=v.1\right \rparen \mathclose {} }}{\scriptscriptstyle \sum _{  \mathopen {}\left \lparen p:u.1=v.1\right \rparen \mathclose {} }} p_*u.2=v.2]]></fr:tex> and the latter is <fr:link
type="local"
href="erct-001G.xml"
addr="erct-001G"
title="N-truncated type"><html:span
xmlns:html="http://www.w3.org/1999/xhtml"
style="white-space: nowrap"><fr:tex
display="inline"><![CDATA[n+1]]></fr:tex>-truncated</html:span></fr:link> by our inductive hypothesis; thus the result follows from <fr:ref
addr="erct-003S"
href="erct-003S.xml"
taxon="Corollary" />.</fr:p>
</fr:mainmatter><fr:backmatter><fr:tree
toc="false"
numbered="false"
show-heading="true"
show-metadata="false"
expanded="true"
root="false"
xmlns:fr="http://www.jonmsterling.com/jms-005P.xml"><fr:frontmatter><fr:title
text="Context">Context</fr:title><fr:authors /></fr:frontmatter><fr:mainmatter><fr:tree
toc="true"
numbered="false"
show-heading="true"
show-metadata="true"
expanded="false"
root="false"
xmlns:fr="http://www.jonmsterling.com/jms-005P.xml"><fr:frontmatter><fr:anchor>3816</fr:anchor><fr:addr
type="user">erct-003W</fr:addr><fr:route>erct-003W.xml</fr:route><fr:title
text="Dependent sum of n-truncated types">Dependent sum of <fr:link
type="local"
href="erct-001G.xml"
addr="erct-001G"
title="N-truncated type"><html:span
xmlns:html="http://www.w3.org/1999/xhtml"
style="white-space: nowrap"><fr:tex
display="inline"><![CDATA[n]]></fr:tex>-truncated</html:span></fr:link> types</fr:title><fr:taxon>Corollary</fr:taxon><fr:date><fr:year>2024</fr:year><fr:month>2</fr:month><fr:day>17</fr:day></fr:date><fr:authors><fr:author><fr:link
type="local"
href="jonmsterling.xml"
addr="jonmsterling"
title="Jon Sterling">Jon Sterling</fr:link></fr:author></fr:authors><fr:meta
name="source">
  
  
  <fr:link
type="external"
href="https://git.sr.ht/~jonsterling/agda-erct/tree/main/item/agda/erct-003W.agda">erct-003W.agda</fr:link>
</fr:meta></fr:frontmatter><fr:mainmatter><fr:p>Let <fr:tex
display="inline"><![CDATA[A]]></fr:tex> be <fr:link
type="local"
href="erct-001G.xml"
addr="erct-001G"
title="N-truncated type"><html:span
xmlns:html="http://www.w3.org/1999/xhtml"
style="white-space: nowrap"><fr:tex
display="inline"><![CDATA[n]]></fr:tex>-truncated</html:span></fr:link> and let <fr:tex
display="inline"><![CDATA[B\colon  A\to \mathsf {Type}]]></fr:tex> be a family of <fr:link
type="local"
href="erct-001G.xml"
addr="erct-001G"
title="N-truncated type"><html:span
xmlns:html="http://www.w3.org/1999/xhtml"
style="white-space: nowrap"><fr:tex
display="inline"><![CDATA[n]]></fr:tex>-truncated</html:span></fr:link> types. Then the dependent sum <fr:tex
display="inline"><![CDATA[\mathchoice {\textstyle \sum _{  \mathopen {}\left \lparen x:A\right \rparen \mathclose {} }}{\textstyle \sum _{  \mathopen {}\left \lparen x:A\right \rparen \mathclose {} }}{\scriptstyle \sum _{  \mathopen {}\left \lparen x:A\right \rparen \mathclose {} }}{\scriptscriptstyle \sum _{  \mathopen {}\left \lparen x:A\right \rparen \mathclose {} }}Bx]]></fr:tex> is <fr:link
type="local"
href="erct-001G.xml"
addr="erct-001G"
title="N-truncated type"><html:span
xmlns:html="http://www.w3.org/1999/xhtml"
style="white-space: nowrap"><fr:tex
display="inline"><![CDATA[n]]></fr:tex>-truncated</html:span></fr:link>.</fr:p>
 
   
   <fr:tree
toc="false"
numbered="true"
show-heading="true"
show-metadata="false"
expanded="true"
root="false"
xmlns:fr="http://www.jonmsterling.com/jms-005P.xml"><fr:frontmatter><fr:anchor>3599</fr:anchor><fr:addr
type="machine">#305</fr:addr><fr:route>unstable-305.xml</fr:route><fr:taxon>Proof</fr:taxon><fr:date><fr:year>2024</fr:year><fr:month>2</fr:month><fr:day>17</fr:day></fr:date><fr:authors><fr:author><fr:link
type="local"
href="jonmsterling.xml"
addr="jonmsterling"
title="Jon Sterling">Jon Sterling</fr:link></fr:author></fr:authors></fr:frontmatter><fr:mainmatter>
 <fr:p>By induction on <fr:tex
display="inline"><![CDATA[n]]></fr:tex>, with the base cases following from <fr:ref
addr="erct-003V"
href="erct-003V.xml"
taxon="Corollary" /> and <fr:ref
addr="erct-001M"
href="erct-001M.xml"
taxon="Lemma" />. In the inductive step, we need to show that for all <fr:tex
display="inline"><![CDATA[u,v\colon \mathchoice {\textstyle \sum _{  \mathopen {}\left \lparen x:A\right \rparen \mathclose {} }}{\textstyle \sum _{  \mathopen {}\left \lparen x:A\right \rparen \mathclose {} }}{\scriptstyle \sum _{  \mathopen {}\left \lparen x:A\right \rparen \mathclose {} }}{\scriptscriptstyle \sum _{  \mathopen {}\left \lparen x:A\right \rparen \mathclose {} }}Bx]]></fr:tex> the identification type <fr:tex
display="inline"><![CDATA[u=v]]></fr:tex> is <fr:link
type="local"
href="erct-001G.xml"
addr="erct-001G"
title="N-truncated type"><html:span
xmlns:html="http://www.w3.org/1999/xhtml"
style="white-space: nowrap"><fr:tex
display="inline"><![CDATA[n+1]]></fr:tex>-truncated</html:span></fr:link> assuming the same of all the identification types of <fr:tex
display="inline"><![CDATA[A]]></fr:tex> and <fr:tex
display="inline"><![CDATA[Bx]]></fr:tex> for <fr:tex
display="inline"><![CDATA[x:A]]></fr:tex>. By <fr:ref
addr="erct-0035"
href="erct-0035.xml"
taxon="Definition" />, <fr:tex
display="inline"><![CDATA[u=v]]></fr:tex> is a <fr:link
type="local"
href="erct-0025.xml"
addr="erct-0025"
title="Retract">retract</fr:link> of <fr:tex
display="inline"><![CDATA[\mathchoice {\textstyle \sum _{  \mathopen {}\left \lparen p:u.1=v.1\right \rparen \mathclose {} }}{\textstyle \sum _{  \mathopen {}\left \lparen p:u.1=v.1\right \rparen \mathclose {} }}{\scriptstyle \sum _{  \mathopen {}\left \lparen p:u.1=v.1\right \rparen \mathclose {} }}{\scriptscriptstyle \sum _{  \mathopen {}\left \lparen p:u.1=v.1\right \rparen \mathclose {} }} p_*u.2=v.2]]></fr:tex> and the latter is <fr:link
type="local"
href="erct-001G.xml"
addr="erct-001G"
title="N-truncated type"><html:span
xmlns:html="http://www.w3.org/1999/xhtml"
style="white-space: nowrap"><fr:tex
display="inline"><![CDATA[n+1]]></fr:tex>-truncated</html:span></fr:link> by our inductive hypothesis; thus the result follows from <fr:ref
addr="erct-003S"
href="erct-003S.xml"
taxon="Corollary" />.</fr:p>
</fr:mainmatter><fr:backmatter /></fr:tree>
 
</fr:mainmatter><fr:backmatter /></fr:tree></fr:mainmatter><fr:backmatter /></fr:tree></fr:backmatter></fr:tree>